irrep/__init__.py
irrep/bandstructure.py
irrep/cli.py
irrep/ebrs.py
irrep/gvectors.py
irrep/kpoint.py
irrep/kpoint_gpaw.py
irrep/or_solutions_obtainer.py
irrep/readfiles.py
irrep/spacegroup.py
irrep/spacegroup_irreps.py
irrep/symmetry_operation.py
irrep/utility.py
irrep/data/msg_numbers.data
irrep/data/ebrs/1.1_ebrs.json
irrep/data/ebrs/1.2_ebrs.json
irrep/data/ebrs/1.3_ebrs.json
irrep/data/ebrs/10.42_ebrs.json
irrep/data/ebrs/10.43_ebrs.json
irrep/data/ebrs/10.44_ebrs.json
irrep/data/ebrs/10.45_ebrs.json
irrep/data/ebrs/10.46_ebrs.json
irrep/data/ebrs/10.47_ebrs.json
irrep/data/ebrs/10.48_ebrs.json
irrep/data/ebrs/10.49_ebrs.json
irrep/data/ebrs/100.171_ebrs.json
irrep/data/ebrs/100.172_ebrs.json
irrep/data/ebrs/100.173_ebrs.json
irrep/data/ebrs/100.174_ebrs.json
irrep/data/ebrs/100.175_ebrs.json
irrep/data/ebrs/100.176_ebrs.json
irrep/data/ebrs/100.177_ebrs.json
irrep/data/ebrs/100.178_ebrs.json
irrep/data/ebrs/100_ebrs.json
irrep/data/ebrs/101.179_ebrs.json
irrep/data/ebrs/101.180_ebrs.json
irrep/data/ebrs/101.181_ebrs.json
irrep/data/ebrs/101.182_ebrs.json
irrep/data/ebrs/101.183_ebrs.json
irrep/data/ebrs/101.184_ebrs.json
irrep/data/ebrs/101.185_ebrs.json
irrep/data/ebrs/101.186_ebrs.json
irrep/data/ebrs/101_ebrs.json
irrep/data/ebrs/102.187_ebrs.json
irrep/data/ebrs/102.188_ebrs.json
irrep/data/ebrs/102.189_ebrs.json
irrep/data/ebrs/102.190_ebrs.json
irrep/data/ebrs/102.191_ebrs.json
irrep/data/ebrs/102.192_ebrs.json
irrep/data/ebrs/102.193_ebrs.json
irrep/data/ebrs/102.194_ebrs.json
irrep/data/ebrs/102_ebrs.json
irrep/data/ebrs/103.195_ebrs.json
irrep/data/ebrs/103.196_ebrs.json
irrep/data/ebrs/103.197_ebrs.json
irrep/data/ebrs/103.198_ebrs.json
irrep/data/ebrs/103.199_ebrs.json
irrep/data/ebrs/103.200_ebrs.json
irrep/data/ebrs/103.201_ebrs.json
irrep/data/ebrs/103.202_ebrs.json
irrep/data/ebrs/103_ebrs.json
irrep/data/ebrs/104.203_ebrs.json
irrep/data/ebrs/104.204_ebrs.json
irrep/data/ebrs/104.205_ebrs.json
irrep/data/ebrs/104.206_ebrs.json
irrep-2.4.1.dist-info/licenses/LICENSE
irrep-2.4.1.dist-info/METADATA
irrep-2.4.1.dist-info/WHEEL
irrep-2.4.1.dist-info/entry_points.txt
irrep-2.4.1.dist-info/top_level.txt
irrep-2.4.1.dist-info/RECORD
