Metadata-Version: 2.4
Name: irrep
Version: 2.4.1
Summary: A tool to get symmetry proberties of ab-initio wavefunctions, irreduible representations and more.
Home-page: https://github.com/irreducible-representations/irrep.git
Author: Stepan S. Tsirkin
Author-email: stepan.tsirkin@ehu.eus
Classifier: Programming Language :: Python :: 3
Classifier: License :: OSI Approved :: GNU General Public License v3 (GPLv3)
Classifier: Operating System :: OS Independent
License-File: LICENSE
Requires-Dist: numpy
Requires-Dist: scipy>=1.0
Requires-Dist: spglib>=2.5.0
Requires-Dist: Click
Requires-Dist: monty
Requires-Dist: ruamel.yaml
Requires-Dist: irreptables>=2.0
Requires-Dist: fortio
Requires-Dist: packaging
Requires-Dist: h5py
Dynamic: author
Dynamic: author-email
Dynamic: classifier
Dynamic: description
Dynamic: description-content-type
Dynamic: home-page
Dynamic: license-file
Dynamic: requires-dist
Dynamic: summary
